[
  {
    "Number": 0,
    "Name": "Level 0",
    "Desc": "Random Shapes!",
    "GameObjects":"",
    "LevelObjects":[]
  },
  {
    "Number": 1,
    "Name": "Level 1",
    "Desc": "Try some Squares",
    "GameObjects":"SSSSSSSSSS",
    "LevelObjects":[]
  },
  {
    "Number": 2,
    "Name": "Level 2",
    "Desc": "Try some Rectangles",
    "GameObjects": "EEEEEEEEEE",
    "LevelObjects":[]
  },
  {
    "Number": 3,
    "Name": "Level 3",
    "Desc": "Try some Circles",
    "GameObjects": "CCCCCCCCCC",
    "LevelObjects":[
    ]
  },
  {
    "Number": 4,
    "Name": "Level 4",
    "Desc": "Try some Triangles",
    "GameObjects": "TITITITITI",
    "LevelObjects":[]
  },
  {
    "Number": 5,
    "Name": "Level 5",
    "Desc": "Try some Rhombuses",
    "GameObjects": "RRRRRRRRRR",
    "LevelObjects":[]
  },
  {
    "Number": 6,
    "Name": "Level 6",
    "Desc": "Try some Hexagons",
    "GameObjects": "HHHHHHHHHH",
    "LevelObjects":[]
  },
  {
    "Number": 7,
    "Name": "Level 7",
    "Desc": "Squares are rectangles",
    "GameObjects":"SESESESESE",
    "LevelObjects":[]
  },
  {
    "Number": 8,
    "Name": "Level 8",
    "Desc": "Up and Down and Round",
    "GameObjects": "TICTICTIC",
    "LevelObjects":[]
  },
  {
    "Number": 9,
    "Name": "Level 9",
    "Desc": "Angles are hard",
    "GameObjects": "RITRITRIT",
    "LevelObjects":[]
  },
  {
    "Number": 10,
    "Name": "Level 10",
    "Desc": "Nothing seems flat",
    "GameObjects": "RRCCHHRRCCHH",
    "LevelObjects":[]
  },
  {
    "Number": 11,
    "Name": "Level 11",
    "Desc": "One of each",
    "GameObjects": "SCTIRHSCTIRH",
    "LevelObjects":[]
  }
]